featureflagclient/__init__.py
featureflagclient/client.py
featureflagclient-0.4.dist-info/METADATA
featureflagclient-0.4.dist-info/RECORD
featureflagclient-0.4.dist-info/WHEEL
featureflagclient-0.4.dist-info/top_level.txt
