Metadata-Version: 2.1
Name: featureflagclient
Version: 0.4
Summary: Service agnostic featureflag client
Home-page: https://github.com/tmaslen/featureflagclient-python
Author: Tom Maslen
Author-email: tom_maslen@hotmail.com
License: UNKNOWN
Download-URL: https://github.com/tmaslen/featureflagclient-python/tarball/master
Keywords: feature flag,feature toggle
Platform: UNKNOWN
